[{"id":0,"firstName":"Jimmy","lastName":"Weimann","city":"West Jacey","title":"National Directives Associate","businessUnit":"Corporate","dept":"Global Digital Group","ext":5861},{"id":1,"firstName":"Margie","lastName":"Leannon","city":"Howe chester","title":"Internal Factors Officer","businessUnit":"Corporate","dept":"Global Digital Group","ext":8466},{"id":2,"firstName":"Louvenia","lastName":"Kulas","city":"Janice borough","title":"District Data Specialist","businessUnit":"Corporate","dept":"Global Digital Group","ext":2521},{"id":3,"firstName":"Alexandrea","lastName":"Brown","city":"Kuhlman view","title":"Direct Marketing Specialist","businessUnit":"Corporate","dept":"Global Digital Group","ext":5662},{"id":4,"firstName":"Douglas","lastName":"Medhurst","city":"East Jennifer burgh","title":"Lead Creative Liason","businessUnit":"Corporate","dept":"Global Digital Group","ext":3172},{"id":5,"firstName":"Syble","lastName":"Morar","city":"North Dana burgh","title":"Lead Paradigm Producer","businessUnit":"Corporate","dept":"Global Digital Group","ext":9502},{"id":6,"firstName":"Dora","lastName":"Breitenberg","city":"New Yolanda","title":"Investor Creative Orchestrator","businessUnit":"Corporate","dept":"Global Digital Group","ext":7355},{"id":7,"firstName":"Ron","lastName":"Weimann","city":"Port Sandy mouth","title":"Forward Applications Associate","businessUnit":"Corporate","dept":"Global Digital Group","ext":9320},{"id":8,"firstName":"Kristoffer","lastName":"Bins","city":"Damien ville","title":"Investor Paradigm Technician","businessUnit":"Corporate","dept":"Global Digital Group","ext":4995},{"id":9,"firstName":"Dudley","lastName":"Feil","city":"Jeffery borough","title":"Future Assurance Architect","businessUnit":"Corporate","dept":"Global Digital Group","ext":4892},{"id":10,"firstName":"Horacio","lastName":"Sauer","city":"Rath haven","title":"National Infrastructure Assistant","businessUnit":"Corporate","dept":"Global Digital Group","ext":2389},{"id":11,"firstName":"Alvina","lastName":"Lindgren","city":"North Quinton","title":"Customer Assurance Representative","businessUnit":"Corporate","dept":"Global Digital Group","ext":6514},{"id":12,"firstName":"Mya","lastName":"Stanton","city":"Lake Jarod","title":"Investor Tactics Manager","businessUnit":"Corporate","dept":"Global Digital Group","ext":9050},{"id":13,"firstName":"Letha","lastName":"McGlynn","city":"Schroeder town","title":"District Group Analyst","businessUnit":"Corporate","dept":"Global Digital Group","ext":4048},{"id":14,"firstName":"Tremaine","lastName":"Dickinson","city":"Port Jakob","title":"Investor Quality Architect","businessUnit":"Corporate","dept":"Global Digital Group","ext":6307},{"id":15,"firstName":"Kennedy","lastName":"Fahey","city":"Wunsch berg","title":"District Optimization Analyst","businessUnit":"Corporate","dept":"Global Digital Group","ext":2000},{"id":16,"firstName":"Celine","lastName":"Funk","city":"Candida town","title":"Dynamic Integration Administrator","businessUnit":"Corporate","dept":"Global Digital Group","ext":2486},{"id":17,"firstName":"Caterina","lastName":"Fahey","city":"Bergnaum stad","title":"Direct Interactions Architect","businessUnit":"Corporate","dept":"Global Digital Group","ext":9974},{"id":18,"firstName":"Brook","lastName":"Ward","city":"North Ethelyn ville","title":"Customer Implementation Architect","businessUnit":"Corporate","dept":"Global Digital Group","ext":8321},{"id":19,"firstName":"Magnus","lastName":"Kuvalis","city":"Gibson ton","title":"Customer Marketing Orchestrator","businessUnit":"Corporate","dept":"Global Digital Group","ext":3117},{"id":20,"firstName":"Myah","lastName":"Ondricka","city":"Champlin shire","title":"Forward Program Engineer","businessUnit":"Corporate","dept":"Global Digital Group","ext":9039},{"id":21,"firstName":"Lila","lastName":"Beer","city":"East Retha furt","title":"Human Applications Administrator","businessUnit":"Corporate","dept":"Global Digital Group","ext":1613},{"id":22,"firstName":"Ludie","lastName":"Crona","city":"West Alfonzo side","title":"Future Interactions Orchestrator","businessUnit":"Corporate","dept":"Global Digital Group","ext":5807},{"id":23,"firstName":"Savanah","lastName":"Keebler","city":"West Vivianne ton","title":"International Branding Engineer","businessUnit":"Corporate","dept":"Global Digital Group","ext":2352},{"id":24,"firstName":"Kareem","lastName":"Emard","city":"Torp port","title":"National Factors Designer","businessUnit":"Corporate","dept":"Global Digital Group","ext":8191},{"id":25,"firstName":"Amira","lastName":"Wolf","city":"Muller ton","title":"Central Factors Assistant","businessUnit":"Corporate","dept":"Global Digital Group","ext":2166},{"id":26,"firstName":"Dagmar","lastName":"Pfeffer","city":"West Vivian","title":"Product Division Consultant","businessUnit":"Corporate","dept":"Global Digital Group","ext":9245},{"id":27,"firstName":"Arnoldo","lastName":"Weber","city":"Keshawn berg","title":"Future Infrastructure Producer","businessUnit":"Corporate","dept":"Global Digital Group","ext":8140},{"id":28,"firstName":"Luz","lastName":"Krajcik","city":"Ricky chester","title":"Product Operations Designer","businessUnit":"Corporate","dept":"Global Digital Group","ext":7872},{"id":29,"firstName":"Clemmie","lastName":"Zboncak","city":"Schmidt borough","title":"Dynamic Division Orchestrator","businessUnit":"Corporate","dept":"Global Digital Group","ext":9724},{"id":30,"firstName":"Josefa","lastName":"Rath","city":"Port Vernie","title":"Chief Integration Facilitator","businessUnit":"Corporate","dept":"Global Digital Group","ext":3769},{"id":31,"firstName":"Alia","lastName":"Hoeger","city":"O'Reilly view","title":"Direct Identity Liason","businessUnit":"Corporate","dept":"Global Digital Group","ext":9463},{"id":32,"firstName":"Nichole","lastName":"Runolfsson","city":"Name burgh","title":"Customer Tactics Administrator","businessUnit":"Corporate","dept":"Global Digital Group","ext":3965},{"id":33,"firstName":"Dexter","lastName":"Bednar","city":"Port Delia chester","title":"Dynamic Accountability Director","businessUnit":"Corporate","dept":"Global Digital Group","ext":6715},{"id":34,"firstName":"Aida","lastName":"Weimann","city":"East Seth berg","title":"Future Communications Analyst","businessUnit":"Corporate","dept":"Global Digital Group","ext":2450},{"id":35,"firstName":"Rowan","lastName":"Hoppe","city":"East Liam","title":"Investor Interactions Coordinator","businessUnit":"Corporate","dept":"Global Digital Group","ext":9723},{"id":36,"firstName":"Garth","lastName":"Howell","city":"West Cyril","title":"Global Solutions Specialist","businessUnit":"Corporate","dept":"Global Digital Group","ext":8549},{"id":37,"firstName":"Misael","lastName":"Reichert","city":"Ledner burgh","title":"Product Quality Administrator","businessUnit":"Corporate","dept":"Global Digital Group","ext":2819},{"id":38,"firstName":"Tyreek","lastName":"Witting","city":"Williamson bury","title":"Investor Web Representative","businessUnit":"Corporate","dept":"Global Digital Group","ext":1366},{"id":39,"firstName":"Sierra","lastName":"Gutmann","city":"New Cordie land","title":"District Program Facilitator","businessUnit":"Corporate","dept":"Global Digital Group","ext":7645},{"id":40,"firstName":"Gus","lastName":"Bogan","city":"Port Darrick stad","title":"National Quality Planner","businessUnit":"Corporate","dept":"Global Digital Group","ext":8746},{"id":41,"firstName":"Hilma","lastName":"Mraz","city":"New Cordia town","title":"Human Division Executive","businessUnit":"Corporate","dept":"Global Digital Group","ext":8702},{"id":42,"firstName":"Catharine","lastName":"Kemmer","city":"Monahan ton","title":"Lead Web Developer","businessUnit":"Corporate","dept":"Global Digital Group","ext":7735},{"id":43,"firstName":"Tyra","lastName":"Moore","city":"Lake Jordan stad","title":"Dynamic Optimization Architect","businessUnit":"Corporate","dept":"Global Digital Group","ext":4003},{"id":44,"firstName":"Erik","lastName":"Koepp","city":"New Aracely","title":"Investor Assurance Developer","businessUnit":"Corporate","dept":"Global Digital Group","ext":8143},{"id":45,"firstName":"Jacky","lastName":"Mitchell","city":"Olson ville","title":"Human Metrics Planner","businessUnit":"Corporate","dept":"Global Digital Group","ext":6581},{"id":46,"firstName":"Gina","lastName":"Legros","city":"North Mozell","title":"International Markets Technician","businessUnit":"Corporate","dept":"Global Digital Group","ext":7011},{"id":47,"firstName":"Franco","lastName":"Gutmann","city":"North Beulah bury","title":"Human Directives Engineer","businessUnit":"Corporate","dept":"Global Digital Group","ext":4064},{"id":48,"firstName":"Easter","lastName":"Fay","city":"South Delia port","title":"Customer Research Officer","businessUnit":"Corporate","dept":"Global Digital Group","ext":3097},{"id":49,"firstName":"Adeline","lastName":"Dickinson","city":"East Pansy view","title":"Customer Optimization Producer","businessUnit":"Corporate","dept":"Global Digital Group","ext":1388},{"id":50,"firstName":"Scotty","lastName":"Brekke","city":"Margarete ton","title":"Regional Brand Executive","businessUnit":"Corporate","dept":"Global Digital Group","ext":3154},{"id":51,"firstName":"Mona","lastName":"Gaylord","city":"North Kailey ville","title":"Forward Marketing Strategist","businessUnit":"Corporate","dept":"Global Digital Group","ext":5032},{"id":52,"firstName":"Chelsie","lastName":"Gibson","city":"Gibson haven","title":"Dynamic Paradigm Director","businessUnit":"Corporate","dept":"Global Digital Group","ext":9138},{"id":53,"firstName":"Cydney","lastName":"Turner","city":"Aron chester","title":"District Program Executive","businessUnit":"Corporate","dept":"Global Digital Group","ext":9126},{"id":54,"firstName":"Alexandra","lastName":"Koch","city":"West Conner","title":"Chief Mobility Manager","businessUnit":"Corporate","dept":"Global Digital Group","ext":8418},{"id":55,"firstName":"Garfield","lastName":"Runolfsson","city":"Hyatt port","title":"Product Mobility Technician","businessUnit":"Corporate","dept":"Global Digital Group","ext":4041},{"id":56,"firstName":"Eulalia","lastName":"Satterfield","city":"East Christophe mouth","title":"Dynamic Paradigm Architect","businessUnit":"Corporate","dept":"Global Digital Group","ext":3401},{"id":57,"firstName":"Emily","lastName":"Dickens","city":"Friesen land","title":"Internal Identity Director","businessUnit":"Corporate","dept":"Global Digital Group","ext":6704},{"id":58,"firstName":"Zetta","lastName":"Lowe","city":"Lake Jane borough","title":"Forward Interactions Planner","businessUnit":"Corporate","dept":"Global Digital Group","ext":4854},{"id":59,"firstName":"Nicholaus","lastName":"Fisher","city":"North Noel","title":"Chief Response Designer","businessUnit":"Corporate","dept":"Global Digital Group","ext":7660},{"id":60,"firstName":"Johnnie","lastName":"Treutel","city":"Senger view","title":"Forward Data Architect","businessUnit":"Corporate","dept":"Global Digital Group","ext":2602},{"id":61,"firstName":"Jolie","lastName":"Bernhard","city":"North Helmer","title":"Senior Integration Coordinator","businessUnit":"Corporate","dept":"Global Digital Group","ext":3064},{"id":62,"firstName":"Brenda","lastName":"Turner","city":"McDermott view","title":"Investor Infrastructure Producer","businessUnit":"Corporate","dept":"Global Digital Group","ext":8255},{"id":63,"firstName":"Fannie","lastName":"Maggio","city":"Ward port","title":"Chief Accountability Representative","businessUnit":"Corporate","dept":"Global Digital Group","ext":9443},{"id":64,"firstName":"Ted","lastName":"Braun","city":"North Natalie land","title":"International Operations Director","businessUnit":"Corporate","dept":"Global Digital Group","ext":2002},{"id":65,"firstName":"Kaylah","lastName":"Roberts","city":"Madilyn burgh","title":"Lead Assurance Specialist","businessUnit":"Corporate","dept":"Global Digital Group","ext":7212},{"id":66,"firstName":"Roel","lastName":"Abshire","city":"Ruecker side","title":"Internal Solutions Producer","businessUnit":"Corporate","dept":"Global Digital Group","ext":9029},{"id":67,"firstName":"Josephine","lastName":"Grady","city":"New Fanny","title":"Dynamic Identity Consultant","businessUnit":"Corporate","dept":"Global Digital Group","ext":1696},{"id":68,"firstName":"Braulio","lastName":"Tillman","city":"Lake Aurore","title":"Dynamic Mobility Analyst","businessUnit":"Corporate","dept":"Global Digital Group","ext":9944},{"id":69,"firstName":"Vicente","lastName":"Emmerich","city":"East Deshaun","title":"District Directives Consultant","businessUnit":"Corporate","dept":"Global Digital Group","ext":9505},{"id":70,"firstName":"Chandler","lastName":"Abshire","city":"Sheldon ville","title":"Product Operations Architect","businessUnit":"Corporate","dept":"Global Digital Group","ext":2701},{"id":71,"firstName":"Ora","lastName":"Ernser","city":"Wilkinson stad","title":"Global Security Strategist","businessUnit":"Corporate","dept":"Global Digital Group","ext":6096},{"id":72,"firstName":"Leta","lastName":"Prohaska","city":"East Clyde ville","title":"Legacy Marketing Executive","businessUnit":"Corporate","dept":"Global Digital Group","ext":2170},{"id":73,"firstName":"Marta","lastName":"Bosco","city":"Port Mylene side","title":"Product Brand Technician","businessUnit":"Corporate","dept":"Global Digital Group","ext":5609},{"id":74,"firstName":"Jerry","lastName":"Okuneva","city":"New Keon","title":"Customer Integration Architect","businessUnit":"Corporate","dept":"Global Digital Group","ext":3464},{"id":75,"firstName":"Stella","lastName":"Schneider","city":"West Kaleb","title":"Global Markets Representative","businessUnit":"Corporate","dept":"Global Digital Group","ext":5700},{"id":76,"firstName":"Marlene","lastName":"Stokes","city":"Homenick stad","title":"Human Factors Coordinator","businessUnit":"Corporate","dept":"Global Digital Group","ext":2044},{"id":77,"firstName":"Gerson","lastName":"Harvey","city":"Erich stad","title":"Investor Brand Coordinator","businessUnit":"Corporate","dept":"Global Digital Group","ext":1489},{"id":78,"firstName":"Mozelle","lastName":"Baumbach","city":"Shawna shire","title":"Forward Usability Facilitator","businessUnit":"Corporate","dept":"Global Digital Group","ext":2925},{"id":79,"firstName":"Tatyana","lastName":"Hegmann","city":"Hills ton","title":"International Marketing Analyst","businessUnit":"Corporate","dept":"Global Digital Group","ext":5533},{"id":80,"firstName":"Lola","lastName":"Lubowitz","city":"Lake Fay","title":"Principal Brand Liason","businessUnit":"Corporate","dept":"Global Digital Group","ext":5477},{"id":81,"firstName":"Rubie","lastName":"Padberg","city":"Baumbach view","title":"Forward Solutions Supervisor","businessUnit":"Corporate","dept":"Global Digital Group","ext":2351},{"id":82,"firstName":"Marquis","lastName":"Huel","city":"Grimes side","title":"International Usability Designer","businessUnit":"Corporate","dept":"Global Digital Group","ext":1479},{"id":83,"firstName":"Myrna","lastName":"Barrows","city":"East Marcus","title":"Lead Marketing Consultant","businessUnit":"Corporate","dept":"Global Digital Group","ext":5065},{"id":84,"firstName":"Taya","lastName":"Block","city":"New Terrell shire","title":"Customer Security Developer","businessUnit":"Corporate","dept":"Global Digital Group","ext":7962},{"id":85,"firstName":"Justine","lastName":"Kris","city":"Darrin shire","title":"International Infrastructure Executive","businessUnit":"Corporate","dept":"Global Digital Group","ext":1773},{"id":86,"firstName":"Ashleigh","lastName":"West","city":"East Kenna","title":"Dynamic Research Liason","businessUnit":"Corporate","dept":"Global Digital Group","ext":3643},{"id":87,"firstName":"Yasmine","lastName":"O'Conner","city":"Port Zula","title":"Product Marketing Architect","businessUnit":"Corporate","dept":"Global Digital Group","ext":9605},{"id":88,"firstName":"Coralie","lastName":"Collins","city":"Lake Frieda","title":"Chief Integration Manager","businessUnit":"Corporate","dept":"Global Digital Group","ext":5209},{"id":89,"firstName":"Romaine","lastName":"Mayer","city":"Kristina land","title":"Legacy Applications Producer","businessUnit":"Corporate","dept":"Global Digital Group","ext":7232},{"id":90,"firstName":"German","lastName":"Auer","city":"Port Nikko borough","title":"Human Data Director","businessUnit":"Corporate","dept":"Global Digital Group","ext":6129},{"id":91,"firstName":"Elnora","lastName":"Schneider","city":"Schulist haven","title":"Customer Configuration Technician","businessUnit":"Corporate","dept":"Global Digital Group","ext":3094},{"id":92,"firstName":"Lenny","lastName":"Mohr","city":"East Lilian","title":"Principal Web Director","businessUnit":"Corporate","dept":"Global Digital Group","ext":3716},{"id":93,"firstName":"Melody","lastName":"Reichert","city":"Davion haven","title":"Dynamic Identity Director","businessUnit":"Corporate","dept":"Global Digital Group","ext":2463},{"id":94,"firstName":"Micheal","lastName":"Goodwin","city":"New Abelardo","title":"Legacy Intranet Agent","businessUnit":"Corporate","dept":"Global Digital Group","ext":9013},{"id":95,"firstName":"Wilfrid","lastName":"Schinner","city":"Port Ivah mouth","title":"Direct Operations Executive","businessUnit":"Corporate","dept":"Global Digital Group","ext":2071},{"id":96,"firstName":"Leonora","lastName":"Fisher","city":"Bruen furt","title":"District Interactions Associate","businessUnit":"Corporate","dept":"Global Digital Group","ext":3862},{"id":97,"firstName":"Nelle","lastName":"Ryan","city":"New Phyllis","title":"Future Intranet Assistant","businessUnit":"Corporate","dept":"Global Digital Group","ext":4931},{"id":98,"firstName":"Lacey","lastName":"Cummings","city":"South Nova","title":"Global Interactions Architect","businessUnit":"Corporate","dept":"Global Digital Group","ext":9066},{"id":99,"firstName":"Alfred","lastName":"Von","city":"South Dina port","title":"Senior Accountability Manager","businessUnit":"Corporate","dept":"Global Digital Group","ext":9762},{"id":100,"firstName":"Alexzander","lastName":"Spinka","city":"West Joshuah","title":"Product Configuration Supervisor","businessUnit":"Corporate","dept":"Global Digital Group","ext":1190},{"id":101,"firstName":"Sim","lastName":"Bauch","city":"Hills chester","title":"Senior Accounts Representative","businessUnit":"Corporate","dept":"Global Digital Group","ext":5968},{"id":102,"firstName":"Daniela","lastName":"Smith","city":"Gleichner burgh","title":"Dynamic Solutions Agent","businessUnit":"Corporate","dept":"Global Digital Group","ext":7864},{"id":103,"firstName":"Salma","lastName":"McLaughlin","city":"New Anastacio","title":"Regional Research Agent","businessUnit":"Corporate","dept":"Global Digital Group","ext":3219},{"id":104,"firstName":"Cassandra","lastName":"Hane","city":"South Monty port","title":"Future Brand Executive","businessUnit":"Corporate","dept":"Global Digital Group","ext":1587},{"id":105,"firstName":"Aisha","lastName":"Lesch","city":"North Frieda","title":"Dynamic Implementation Developer","businessUnit":"Corporate","dept":"Global Digital Group","ext":2294},{"id":106,"firstName":"Camren","lastName":"Blick","city":"East Theresa haven","title":"Customer Data Facilitator","businessUnit":"Corporate","dept":"Global Digital Group","ext":5855},{"id":107,"firstName":"Julian","lastName":"Lesch","city":"Tremaine burgh","title":"Investor Response Director","businessUnit":"Corporate","dept":"Global Digital Group","ext":5980},{"id":108,"firstName":"Libby","lastName":"Jerde","city":"Huels mouth","title":"Legacy Response Officer","businessUnit":"Corporate","dept":"Global Digital Group","ext":7944},{"id":109,"firstName":"Kristina","lastName":"Stoltenberg","city":"Julio bury","title":"Principal Assurance Liason","businessUnit":"Corporate","dept":"Global Digital Group","ext":3114},{"id":110,"firstName":"Korey","lastName":"Cole","city":"Ottis town","title":"Legacy Infrastructure Executive","businessUnit":"Corporate","dept":"Global Digital Group","ext":6108},{"id":111,"firstName":"Maximus","lastName":"Schroeder","city":"East Khalid land","title":"Direct Web Agent","businessUnit":"Corporate","dept":"Global Digital Group","ext":1815},{"id":112,"firstName":"Joelle","lastName":"Douglas","city":"O'Hara port","title":"Future Brand Assistant","businessUnit":"Corporate","dept":"Global Digital Group","ext":1544},{"id":113,"firstName":"Raphaelle","lastName":"Gleason","city":"South Mohammed","title":"Central Creative Liason","businessUnit":"Corporate","dept":"Global Digital Group","ext":3526},{"id":114,"firstName":"Aylin","lastName":"Langosh","city":"Port Mervin","title":"Product Metrics Analyst","businessUnit":"Corporate","dept":"Global Digital Group","ext":7297},{"id":115,"firstName":"Gabriel","lastName":"Gusikowski","city":"Buckridge view","title":"Dynamic Marketing Specialist","businessUnit":"Corporate","dept":"Global Digital Group","ext":3247},{"id":116,"firstName":"Carli","lastName":"Kautzer","city":"South Noemi port","title":"Investor Tactics Coordinator","businessUnit":"Corporate","dept":"Global Digital Group","ext":9057},{"id":117,"firstName":"Augusta","lastName":"Runolfsson","city":"New Euna mouth","title":"International Accountability Supervisor","businessUnit":"Corporate","dept":"Global Digital Group","ext":6771},{"id":118,"firstName":"Urban","lastName":"Wiza","city":"Lake Maryjane port","title":"Internal Solutions Agent","businessUnit":"Corporate","dept":"Global Digital Group","ext":9252},{"id":119,"firstName":"Kameron","lastName":"Schmitt","city":"Crist furt","title":"Principal Integration Strategist","businessUnit":"Corporate","dept":"Global Digital Group","ext":4002},{"id":120,"firstName":"Zander","lastName":"Heathcote","city":"Hoeger land","title":"Principal Data Analyst","businessUnit":"Corporate","dept":"Global Digital Group","ext":8930},{"id":121,"firstName":"Chance","lastName":"Glover","city":"West Ashlynn ville","title":"Legacy Applications Orchestrator","businessUnit":"Corporate","dept":"Global Digital Group","ext":4246},{"id":122,"firstName":"Eliseo","lastName":"Glover","city":"Turcotte mouth","title":"Forward Paradigm Supervisor","businessUnit":"Corporate","dept":"Global Digital Group","ext":1118},{"id":123,"firstName":"Jennings","lastName":"Emard","city":"Lincoln view","title":"Lead Division Designer","businessUnit":"Corporate","dept":"Global Digital Group","ext":9825},{"id":124,"firstName":"Fabian","lastName":"Dibbert","city":"Langworth port","title":"Chief Security Producer","businessUnit":"Corporate","dept":"Global Digital Group","ext":5438},{"id":125,"firstName":"Royce","lastName":"Ward","city":"Lake Serenity","title":"Forward Directives Producer","businessUnit":"Corporate","dept":"Global Digital Group","ext":9062},{"id":126,"firstName":"Alexandra","lastName":"Connelly","city":"Strosin stad","title":"District Applications Producer","businessUnit":"Corporate","dept":"Global Digital Group","ext":8932},{"id":127,"firstName":"Kristian","lastName":"Treutel","city":"Port Leon shire","title":"Customer Marketing Manager","businessUnit":"Corporate","dept":"Global Digital Group","ext":3279},{"id":128,"firstName":"Filomena","lastName":"Ziemann","city":"Kohler ton","title":"International Web Architect","businessUnit":"Corporate","dept":"Global Digital Group","ext":8064},{"id":129,"firstName":"Sven","lastName":"Turcotte","city":"South Kolby haven","title":"Corporate Configuration Executive","businessUnit":"Corporate","dept":"Global Digital Group","ext":9604},{"id":130,"firstName":"Macey","lastName":"Heller","city":"Julien berg","title":"Customer Web Director","businessUnit":"Corporate","dept":"Global Digital Group","ext":3830},{"id":131,"firstName":"Kraig","lastName":"Miller","city":"Adams mouth","title":"International Group Specialist","businessUnit":"Corporate","dept":"Global Digital Group","ext":2404},{"id":132,"firstName":"Gonzalo","lastName":"Pfeffer","city":"Lake Stephania","title":"National Solutions Architect","businessUnit":"Corporate","dept":"Global Digital Group","ext":3638},{"id":133,"firstName":"Christy","lastName":"O'Keefe","city":"East Adonis","title":"Dynamic Directives Representative","businessUnit":"Corporate","dept":"Global Digital Group","ext":4030},{"id":134,"firstName":"Levi","lastName":"Ankunding","city":"Port Jalon borough","title":"National Data Strategist","businessUnit":"Corporate","dept":"Global Digital Group","ext":7043},{"id":135,"firstName":"Zoey","lastName":"MacGyver","city":"Reggie mouth","title":"Product Web Consultant","businessUnit":"Corporate","dept":"Global Digital Group","ext":3955},{"id":136,"firstName":"Nelle","lastName":"Gulgowski","city":"West Kiley","title":"Lead Directives Analyst","businessUnit":"Corporate","dept":"Global Digital Group","ext":9619},{"id":137,"firstName":"Danial","lastName":"Dietrich","city":"Harvey haven","title":"Forward Metrics Assistant","businessUnit":"Corporate","dept":"Global Digital Group","ext":1236},{"id":138,"firstName":"Marques","lastName":"Gorczany","city":"Tremblay burgh","title":"Central Group Assistant","businessUnit":"Corporate","dept":"Global Digital Group","ext":7356},{"id":139,"firstName":"Gene","lastName":"Ondricka","city":"Iliana ville","title":"Chief Quality Orchestrator","businessUnit":"Corporate","dept":"Global Digital Group","ext":2311},{"id":140,"firstName":"Kaia","lastName":"Boehm","city":"Jasen shire","title":"Investor Communications Producer","businessUnit":"Corporate","dept":"Global Digital Group","ext":9371},{"id":141,"firstName":"Ashleigh","lastName":"Lueilwitz","city":"Delphine view","title":"District Marketing Associate","businessUnit":"Corporate","dept":"Global Digital Group","ext":8294},{"id":142,"firstName":"Chanelle","lastName":"Quigley","city":"Port Charlene","title":"Future Implementation Architect","businessUnit":"Corporate","dept":"Global Digital Group","ext":6988},{"id":143,"firstName":"Simeon","lastName":"Heller","city":"North Sydnee","title":"National Infrastructure Assistant","businessUnit":"Corporate","dept":"Global Digital Group","ext":3384},{"id":144,"firstName":"Norris","lastName":"Bins","city":"Johan ville","title":"National Functionality Director","businessUnit":"Corporate","dept":"Global Digital Group","ext":3618},{"id":145,"firstName":"Ricardo","lastName":"Tremblay","city":"Christine bury","title":"Investor Directives Executive","businessUnit":"Corporate","dept":"Global Digital Group","ext":8897},{"id":146,"firstName":"Gabrielle","lastName":"Murazik","city":"New Grover","title":"Future Solutions Consultant","businessUnit":"Corporate","dept":"Global Digital Group","ext":5198},{"id":147,"firstName":"Ali","lastName":"Donnelly","city":"Lake Jared","title":"Global Web Manager","businessUnit":"Corporate","dept":"Global Digital Group","ext":2142},{"id":148,"firstName":"Alisa","lastName":"Wolf","city":"East Jana mouth","title":"Customer Division Assistant","businessUnit":"Corporate","dept":"Global Digital Group","ext":8708},{"id":149,"firstName":"Gretchen","lastName":"O'Keefe","city":"Alta stad","title":"Principal Data Officer","businessUnit":"Corporate","dept":"Global Digital Group","ext":3646}]